magic_flux_led/__init__.py
magic_flux_led/__main__.py
magic_flux_led-0.25.dist-info/LICENSE
magic_flux_led-0.25.dist-info/METADATA
magic_flux_led-0.25.dist-info/WHEEL
magic_flux_led-0.25.dist-info/entry_points.txt
magic_flux_led-0.25.dist-info/top_level.txt
magic_flux_led-0.25.dist-info/RECORD
