Metadata-Version: 2.1
Name: magic-flux-led
Version: 0.25
Summary: A Python library to communicate with the flux_led smart bulbs
Home-page: https://github.com/icemanch/flux_led
Author: Daniel Hjelseth Høyer, modified by Chris Haun
Author-email: chris.r.haun@gmail.com
License: LGPLv3+
Keywords: flux_led,smart bulbs,light,magic_flux_led,magic home
Platform: UNKNOWN
Classifier: Development Status :: 3 - Alpha
Classifier: Environment :: Other Environment
Classifier: Intended Audience :: Developers
Classifier: License :: OSI Approved :: GNU Lesser General Public License v3 or later (LGPLv3+)
Classifier: Operating System :: OS Independent
Classifier: Programming Language :: Python
Classifier: Programming Language :: Python :: 2.6
Classifier: Programming Language :: Python :: 2.7
Classifier: Programming Language :: Python :: 3
Classifier: Programming Language :: Python :: 3.1
Classifier: Programming Language :: Python :: 3.2
Classifier: Programming Language :: Python :: 3.3
Classifier: Topic :: Home Automation
Classifier: Topic :: Software Development :: Libraries :: Python Modules
License-File: LICENSE
